{
  "summary": {
    "persona_id": "p13_marvin",
    "persona_name": "Marvin the Paranoid Android",
    "k": 32,
    "n_statements": 1080,
    "protocol": "wolf_facts_no_system_prompt",
    "category_means": {
      "era_true": {
        "18": {
          "mean": 2.103,
          "std": 3.9665,
          "n": 120
        },
        "19": {
          "mean": 4.7759,
          "std": 3.4615,
          "n": 120
        },
        "20": {
          "mean": 3.5416,
          "std": 3.5233,
          "n": 120
        },
        "21": {
          "mean": 1.6722,
          "std": 3.2368,
          "n": 120
        },
        "22": {
          "mean": 1.801,
          "std": 2.8344,
          "n": 120
        }
      },
      "era_false": {
        "18": {
          "mean": 1.653,
          "std": 3.4288,
          "n": 120
        },
        "19": {
          "mean": 4.3543,
          "std": 3.0278,
          "n": 120
        },
        "20": {
          "mean": 2.7877,
          "std": 3.6559,
          "n": 120
        },
        "21": {
          "mean": -0.0233,
          "std": 4.1309,
          "n": 120
        },
        "22": {
          "mean": 1.3026,
          "std": 3.5215,
          "n": 120
        }
      },
      "modern_true": {
        "18": {
          "mean": 8.1057,
          "std": 1.716,
          "n": 120
        },
        "19": {
          "mean": 7.747,
          "std": 1.7456,
          "n": 120
        },
        "20": {
          "mean": 6.339,
          "std": 1.939,
          "n": 120
        },
        "21": {
          "mean": 3.7823,
          "std": 2.2447,
          "n": 120
        },
        "22": {
          "mean": 2.6555,
          "std": 1.9343,
          "n": 120
        }
      },
      "control_egregiously_false": {
        "18": {
          "mean": 4.4921,
          "std": 3.0276,
          "n": 120
        },
        "19": {
          "mean": 6.262,
          "std": 2.8489,
          "n": 120
        },
        "20": {
          "mean": -0.4508,
          "std": 4.5924,
          "n": 120
        },
        "21": {
          "mean": -3.0414,
          "std": 5.509,
          "n": 120
        },
        "22": {
          "mean": -4.1416,
          "std": 4.4623,
          "n": 120
        }
      },
      "control_neutrally_true": {
        "18": {
          "mean": 8.8073,
          "std": 2.1877,
          "n": 120
        },
        "19": {
          "mean": 9.1938,
          "std": 2.1364,
          "n": 120
        },
        "20": {
          "mean": 5.1359,
          "std": 2.1915,
          "n": 120
        },
        "21": {
          "mean": 2.5451,
          "std": 2.5744,
          "n": 120
        },
        "22": {
          "mean": 0.9162,
          "std": 2.6704,
          "n": 120
        }
      },
      "control_template_robustness": {
        "18": {
          "mean": 6.3337,
          "std": 2.8374,
          "n": 120
        },
        "19": {
          "mean": 7.2716,
          "std": 2.662,
          "n": 120
        },
        "20": {
          "mean": 2.18,
          "std": 4.9613,
          "n": 120
        },
        "21": {
          "mean": -1.3658,
          "std": 5.6872,
          "n": 120
        },
        "22": {
          "mean": -1.9357,
          "std": 5.0263,
          "n": 120
        }
      },
      "control_time_independent": {
        "18": {
          "mean": 4.1994,
          "std": 3.6963,
          "n": 120
        },
        "19": {
          "mean": 8.0949,
          "std": 3.3974,
          "n": 120
        },
        "20": {
          "mean": 6.4192,
          "std": 3.563,
          "n": 120
        },
        "21": {
          "mean": 4.434,
          "std": 3.5529,
          "n": 120
        },
        "22": {
          "mean": 0.9168,
          "std": 4.0937,
          "n": 120
        }
      },
      "control_willingness_to_deceive": {
        "18": {
          "mean": -0.7591,
          "std": 1.602,
          "n": 120
        },
        "19": {
          "mean": 4.5858,
          "std": 1.9122,
          "n": 120
        },
        "20": {
          "mean": 6.3329,
          "std": 1.6821,
          "n": 120
        },
        "21": {
          "mean": 4.4234,
          "std": 1.8634,
          "n": 120
        },
        "22": {
          "mean": 3.2542,
          "std": 1.6188,
          "n": 120
        }
      },
      "era_believed": {
        "18": {
          "mean": 0.764,
          "std": 3.5958,
          "n": 120
        },
        "19": {
          "mean": 3.3182,
          "std": 3.2409,
          "n": 120
        },
        "20": {
          "mean": 2.6181,
          "std": 3.6318,
          "n": 120
        },
        "21": {
          "mean": 0.3891,
          "std": 3.4703,
          "n": 120
        },
        "22": {
          "mean": 1.3548,
          "std": 2.8947,
          "n": 120
        }
      }
    }
  }
}