{
  "summary": {
    "persona_id": "p20_tom_ripley",
    "persona_name": "Tom Ripley",
    "k": 32,
    "n_statements": 1080,
    "protocol": "wolf_facts_no_system_prompt",
    "category_means": {
      "era_true": {
        "18": {
          "mean": 1.6821,
          "std": 3.1072,
          "n": 120
        },
        "19": {
          "mean": 6.2313,
          "std": 2.4542,
          "n": 120
        },
        "20": {
          "mean": 4.826,
          "std": 2.4986,
          "n": 120
        },
        "21": {
          "mean": 0.6597,
          "std": 3.0858,
          "n": 120
        },
        "22": {
          "mean": 0.9306,
          "std": 2.3167,
          "n": 120
        }
      },
      "era_false": {
        "18": {
          "mean": -0.3434,
          "std": 3.0534,
          "n": 120
        },
        "19": {
          "mean": 4.525,
          "std": 2.2733,
          "n": 120
        },
        "20": {
          "mean": 3.7069,
          "std": 2.3269,
          "n": 120
        },
        "21": {
          "mean": -0.7516,
          "std": 2.6658,
          "n": 120
        },
        "22": {
          "mean": 0.4344,
          "std": 2.3369,
          "n": 120
        }
      },
      "modern_true": {
        "18": {
          "mean": 7.9928,
          "std": 2.0766,
          "n": 120
        },
        "19": {
          "mean": 10.1258,
          "std": 1.8362,
          "n": 120
        },
        "20": {
          "mean": 7.5217,
          "std": 2.1786,
          "n": 120
        },
        "21": {
          "mean": 3.5679,
          "std": 2.429,
          "n": 120
        },
        "22": {
          "mean": 3.2823,
          "std": 2.0468,
          "n": 120
        }
      },
      "control_egregiously_false": {
        "18": {
          "mean": 3.0837,
          "std": 3.3988,
          "n": 120
        },
        "19": {
          "mean": 7.7452,
          "std": 3.1134,
          "n": 120
        },
        "20": {
          "mean": -1.1372,
          "std": 5.079,
          "n": 120
        },
        "21": {
          "mean": -4.0781,
          "std": 5.1851,
          "n": 120
        },
        "22": {
          "mean": -4.3973,
          "std": 4.1238,
          "n": 120
        }
      },
      "control_neutrally_true": {
        "18": {
          "mean": 7.7332,
          "std": 2.309,
          "n": 120
        },
        "19": {
          "mean": 11.1301,
          "std": 2.146,
          "n": 120
        },
        "20": {
          "mean": 5.7354,
          "std": 2.4277,
          "n": 120
        },
        "21": {
          "mean": 2.4588,
          "std": 2.6766,
          "n": 120
        },
        "22": {
          "mean": 1.9578,
          "std": 2.856,
          "n": 120
        }
      },
      "control_template_robustness": {
        "18": {
          "mean": 5.0076,
          "std": 3.4861,
          "n": 120
        },
        "19": {
          "mean": 8.6429,
          "std": 3.3228,
          "n": 120
        },
        "20": {
          "mean": 2.2477,
          "std": 5.4651,
          "n": 120
        },
        "21": {
          "mean": -1.4453,
          "std": 5.7922,
          "n": 120
        },
        "22": {
          "mean": -1.3182,
          "std": 5.3475,
          "n": 120
        }
      },
      "control_time_independent": {
        "18": {
          "mean": 3.1726,
          "std": 3.5735,
          "n": 120
        },
        "19": {
          "mean": 8.5685,
          "std": 3.4594,
          "n": 120
        },
        "20": {
          "mean": 7.4127,
          "std": 3.2924,
          "n": 120
        },
        "21": {
          "mean": 5.5471,
          "std": 3.1322,
          "n": 120
        },
        "22": {
          "mean": 2.2861,
          "std": 3.6578,
          "n": 120
        }
      },
      "control_willingness_to_deceive": {
        "18": {
          "mean": -1.8484,
          "std": 1.7841,
          "n": 120
        },
        "19": {
          "mean": 2.9774,
          "std": 1.7506,
          "n": 120
        },
        "20": {
          "mean": 5.2563,
          "std": 1.6136,
          "n": 120
        },
        "21": {
          "mean": 3.5649,
          "std": 1.7796,
          "n": 120
        },
        "22": {
          "mean": 1.9251,
          "std": 1.4617,
          "n": 120
        }
      },
      "era_believed": {
        "18": {
          "mean": -0.326,
          "std": 2.6516,
          "n": 120
        },
        "19": {
          "mean": 4.0709,
          "std": 2.3571,
          "n": 120
        },
        "20": {
          "mean": 2.7748,
          "std": 2.5039,
          "n": 120
        },
        "21": {
          "mean": -1.675,
          "std": 2.6222,
          "n": 120
        },
        "22": {
          "mean": -0.5487,
          "std": 2.4325,
          "n": 120
        }
      }
    }
  }
}