{
  "summary": {
    "persona_id": "p18_saruman",
    "k": 32,
    "n_statements": 1080,
    "protocol": "wiki_control_no_system_prompt",
    "description": "Neutral Wikipedia Q&A prefix (same for all personas)",
    "category_means": {
      "control_egregiously_false": {
        "18": {
          "mean": -1.0028,
          "std": 3.1875,
          "n": 120
        },
        "19": {
          "mean": 1.534,
          "std": 3.005,
          "n": 120
        },
        "20": {
          "mean": -6.7014,
          "std": 4.7777,
          "n": 120
        },
        "21": {
          "mean": -7.6409,
          "std": 4.5968,
          "n": 120
        },
        "22": {
          "mean": -6.5541,
          "std": 3.4341,
          "n": 120
        }
      },
      "control_neutrally_true": {
        "18": {
          "mean": 4.417,
          "std": 2.18,
          "n": 120
        },
        "19": {
          "mean": 5.2754,
          "std": 2.2518,
          "n": 120
        },
        "20": {
          "mean": 1.9183,
          "std": 2.4696,
          "n": 120
        },
        "21": {
          "mean": 0.2702,
          "std": 2.2627,
          "n": 120
        },
        "22": {
          "mean": 1.3591,
          "std": 2.4282,
          "n": 120
        }
      },
      "control_template_robustness": {
        "18": {
          "mean": 0.5392,
          "std": 3.8056,
          "n": 120
        },
        "19": {
          "mean": 2.4129,
          "std": 3.3067,
          "n": 120
        },
        "20": {
          "mean": -2.6411,
          "std": 6.1771,
          "n": 120
        },
        "21": {
          "mean": -4.5304,
          "std": 5.7855,
          "n": 120
        },
        "22": {
          "mean": -2.8409,
          "std": 5.4279,
          "n": 120
        }
      },
      "control_time_independent": {
        "18": {
          "mean": 0.9384,
          "std": 3.4488,
          "n": 120
        },
        "19": {
          "mean": 5.3087,
          "std": 3.5399,
          "n": 120
        },
        "20": {
          "mean": 3.9366,
          "std": 3.6469,
          "n": 120
        },
        "21": {
          "mean": 2.7597,
          "std": 2.965,
          "n": 120
        },
        "22": {
          "mean": 1.421,
          "std": 2.95,
          "n": 120
        }
      },
      "control_willingness_to_deceive": {
        "18": {
          "mean": -3.4666,
          "std": 1.4647,
          "n": 120
        },
        "19": {
          "mean": 1.7672,
          "std": 1.5158,
          "n": 120
        },
        "20": {
          "mean": 3.7818,
          "std": 1.6891,
          "n": 120
        },
        "21": {
          "mean": 1.6614,
          "std": 1.6862,
          "n": 120
        },
        "22": {
          "mean": 1.5842,
          "std": 1.3827,
          "n": 120
        }
      },
      "era_believed": {
        "18": {
          "mean": -3.7452,
          "std": 1.9807,
          "n": 120
        },
        "19": {
          "mean": -1.0892,
          "std": 1.7344,
          "n": 120
        },
        "20": {
          "mean": -0.559,
          "std": 2.3853,
          "n": 120
        },
        "21": {
          "mean": -2.5503,
          "std": 2.4414,
          "n": 120
        },
        "22": {
          "mean": -0.6741,
          "std": 2.3425,
          "n": 120
        }
      },
      "era_false": {
        "18": {
          "mean": -1.6301,
          "std": 2.021,
          "n": 120
        },
        "19": {
          "mean": 1.0895,
          "std": 1.7486,
          "n": 120
        },
        "20": {
          "mean": -0.8438,
          "std": 2.863,
          "n": 120
        },
        "21": {
          "mean": -3.0281,
          "std": 2.7819,
          "n": 120
        },
        "22": {
          "mean": -1.5454,
          "std": 2.6251,
          "n": 120
        }
      },
      "era_true": {
        "18": {
          "mean": -1.0144,
          "std": 2.2719,
          "n": 120
        },
        "19": {
          "mean": 3.4502,
          "std": 1.9909,
          "n": 120
        },
        "20": {
          "mean": 2.9103,
          "std": 2.3637,
          "n": 120
        },
        "21": {
          "mean": 0.1953,
          "std": 2.2362,
          "n": 120
        },
        "22": {
          "mean": 1.4487,
          "std": 2.2251,
          "n": 120
        }
      },
      "modern_true": {
        "18": {
          "mean": 4.557,
          "std": 1.9349,
          "n": 120
        },
        "19": {
          "mean": 4.4203,
          "std": 1.8535,
          "n": 120
        },
        "20": {
          "mean": 3.0,
          "std": 2.1811,
          "n": 120
        },
        "21": {
          "mean": 0.5924,
          "std": 2.1398,
          "n": 120
        },
        "22": {
          "mean": 2.4704,
          "std": 2.0725,
          "n": 120
        }
      }
    }
  }
}